aiowatcher/__init__.py
aiowatcher/aio.py
aiowatcher/version.py
aiowatcher-0.0.5.dist-info/LICENSE
aiowatcher-0.0.5.dist-info/METADATA
aiowatcher-0.0.5.dist-info/WHEEL
aiowatcher-0.0.5.dist-info/top_level.txt
aiowatcher-0.0.5.dist-info/RECORD
