Metadata-Version: 2.1
Name: aiowatcher
Version: 0.0.5
Summary: Asynchronous library to watch files in real time.
Home-page: https://github.com/py-paulo/aiowatcher.git
Author: Paulo Roberto <paulo.rb.beserra@gmail.com>
Author-email: paulo.rb.beserra@gmail.com
License: Apache 2
Project-URL: GitHub: issues, https://github.com/py-paulo/aiowatcher/issues
Project-URL: GitHub: repo, https://github.com/py-paulo/aiowatcher
Keywords: aio,python,asyncio,fileio,io
Platform: UNKNOWN
Classifier: Environment :: Console
Classifier: Programming Language :: Python :: 3
Classifier: Programming Language :: Python :: 3.6
Classifier: Programming Language :: Python :: 3.7
Classifier: Programming Language :: Python :: 3.8
Classifier: Operating System :: POSIX
Classifier: Operating System :: MacOS :: MacOS X
Classifier: Operating System :: Microsoft :: Windows
Classifier: Framework :: AsyncIO
Provides: aiowatcher
Requires-Python: >=3.6
Requires-Dist: aiofile (~=3.1.0)
